basek2/__init__.py
basek2/player.py
basek2/team.py
basek2-0.0.0.3.dist-info/METADATA
basek2-0.0.0.3.dist-info/WHEEL
basek2-0.0.0.3.dist-info/top_level.txt
basek2-0.0.0.3.dist-info/RECORD
